msgraph_async_beta/__init__.py
msgraph_async_beta/client/__init__.py
msgraph_async_beta/client/client.py
msgraph_async_beta/client/tests/__init__.py
msgraph_async_beta/client/tests/test_client.py
msgraph_async_beta/common/__init__.py
msgraph_async_beta/common/constants.py
msgraph_async_beta/common/exceptions.py
msgraph_async_beta/common/odata_query.py
msgraph_async_beta/common/tests/__init__.py
msgraph_async_beta/common/tests/test_odata_query.py
msgraph_async_beta/common/tests/test_subscription_resource.py
msgraph_async_beta-0.0.2.dist-info/LICENSE
msgraph_async_beta-0.0.2.dist-info/METADATA
msgraph_async_beta-0.0.2.dist-info/WHEEL
msgraph_async_beta-0.0.2.dist-info/top_level.txt
msgraph_async_beta-0.0.2.dist-info/RECORD
