Metadata-Version: 2.1
Name: msgraph-async-beta
Version: 0.0.2
Summary: Client for using Microsoft Graph API asynchronously
Home-page: https://noamm91.github.io/msgraph-async
Author: Noam Meerovitch
Author-email: noamm91@gmail.com
License: UNKNOWN
Platform: UNKNOWN
Classifier: Programming Language :: Python :: 3
Classifier: License :: OSI Approved :: MIT License
Classifier: Operating System :: OS Independent
Requires-Python: >=3.6
License-File: LICENSE
